newsapi/__init__.py
newsapi/articles.py
newsapi/base_news.py
newsapi/sources.py
newsapi-0.1.1.dist-info/DESCRIPTION.rst
newsapi-0.1.1.dist-info/METADATA
newsapi-0.1.1.dist-info/RECORD
newsapi-0.1.1.dist-info/WHEEL
newsapi-0.1.1.dist-info/metadata.json
newsapi-0.1.1.dist-info/top_level.txt
