Metadata-Version: 1.1
Name: newsapi
Version: 0.1.1
Summary: A python wrapper for News API (newsapi.org)
Home-page: https://github.com/slapbot/newsapi
Author: Ujjwal Gupta
Author-email: ugupta41@gmail.com
License: MIT
Keywords: pynewsapi newsapi newsapi.org news api-client news-feed newsfeeder
Platform: UNKNOWN
Classifier: Development Status :: 3 - Alpha
Classifier: Environment :: Web Environment
Classifier: Environment :: Console Environment
Classifier: Operating System :: OS Independent
Classifier: Intended Audience :: Developers
Classifier: Topic :: Software Development :: Build Tools
Classifier: License :: OSI Approved :: MIT License
Classifier: Programming Language :: Python
Classifier: Programming Language :: Python :: 3
Classifier: Programming Language :: Python :: 3.3
Classifier: Programming Language :: Python :: 3.4
Classifier: Programming Language :: Python :: 3.5
